devolutions_crypto\__init__.py
devolutions_crypto\__init__.pyi
devolutions_crypto\devolutions_crypto.cp312-win_amd64.pyd
devolutions_crypto\py.typed
devolutions_crypto-2026.1.13.dist-info\METADATA
devolutions_crypto-2026.1.13.dist-info\WHEEL
devolutions_crypto.pyi
devolutions_crypto-2026.1.13.dist-info\RECORD
