Metadata-Version: 2.4
Name: devolutions-crypto
Version: 2026.1.13
Classifier: Development Status :: 4 - Beta
Classifier: Intended Audience :: Developers
Classifier: License :: OSI Approved :: MIT License
Classifier: License :: OSI Approved :: Apache Software License
Classifier: Programming Language :: Python :: 3
Classifier: Programming Language :: Rust
Classifier: Topic :: Security :: Cryptography
Summary: An abstraction layer for the cryptography used by Devolutions
Author-email: Philippe Dugre <pdugre@devolutions.net>, Mathieu Morrissette <mmorrissette@devolutions.net>
License: MIT OR Apache-2.0
Requires-Python: >=3.10
Project-URL: Homepage, https://github.com/devolutions/devolutions-crypto
Project-URL: Repository, https://github.com/devolutions/devolutions-crypto
